github_switcher/__init__.py
github_switcher/cli.py
github_switcher/config.py
github_switcher/git_manager.py
github_switcher/profiles.py
github_switcher/ssh_manager.py
github_switcher/utils.py
github_switcher/wizard.py
github_switcher-0.2.0.dist-info/WHEEL
github_switcher-0.2.0.dist-info/entry_points.txt
github_switcher-0.2.0.dist-info/METADATA
github_switcher-0.2.0.dist-info/RECORD
