Metadata-Version: 2.3
Name: github-switcher
Version: 0.2.0
Summary: Professional CLI tool for managing multiple GitHub identities with wizard-based profile creation and SSH key management
Keywords: github,ssh,git,identity,cli,profile,switcher
Author: Mostafa Gamil
Author-email: Mostafa Gamil <mostafa_gamil@yahoo.com>
License: MIT
Classifier: Development Status :: 4 - Beta
Classifier: Intended Audience :: Developers
Classifier: License :: OSI Approved :: MIT License
Classifier: Operating System :: OS Independent
Classifier: Programming Language :: Python :: 3
Classifier: Programming Language :: Python :: 3.10
Classifier: Programming Language :: Python :: 3.11
Classifier: Programming Language :: Python :: 3.12
Classifier: Topic :: Software Development
Classifier: Topic :: Utilities
Requires-Dist: typer>=0.12.0
Requires-Dist: rich>=13.0.0
Requires-Dist: toml>=0.10.2
Requires-Dist: paramiko>=3.0.0
Requires-Dist: pyperclip>=1.8.0
Requires-Dist: cryptography>=41.0.0
Requires-Dist: pytest>=7.0.0 ; extra == 'dev'
Requires-Dist: pytest-cov>=4.0.0 ; extra == 'dev'
Requires-Dist: mypy>=1.5.0 ; extra == 'dev'
Requires-Dist: ruff>=0.1.0 ; extra == 'dev'
Requires-Dist: pre-commit>=3.0.0 ; extra == 'dev'
Requires-Python: >=3.10
Project-URL: Changelog, https://github.com/mostafagamil/Github-Switcher/blob/main/CHANGELOG.md
Project-URL: Homepage, https://github.com/mostafagamil/Github-Switcher
Project-URL: Issues, https://github.com/mostafagamil/Github-Switcher/issues
Project-URL: Repository, https://github.com/mostafagamil/Github-Switcher
Provides-Extra: dev
